fifo/RTL/fifo.sv
// =======================================================================
// Module Name	: my_fifo
// Author	: Kim Daeyeong
// Date		: 2026-03-18
//
// Description	:
// 	Parameteriable synchronous FIFO buffer with general RTL structure
// 	(combinational + sequential logic)
//
// 	- Single clock
// 	- Supports simultaneous read/write operation
// 	- Provides full, empty, almost full, almost empty flag signals
//	
//	Data is written into the FIFO when 'wr' is asserted and Fifo is 
//	not Full. Data is read from the FIFO when 'rd' is asserted and 
//	FIfo is not empty.
//
//	The FIFO uses circular pointer addressing and extra bit for 
//	overaround.
//
// Parameters	:
// 	DATA_WIDTH	  : width of stored data
// 	FIFO_WIDTH	  : WIDTH of FIFO (number of entries)
// 	AFULL_THRESHOLD	  : almost full flag threshold
// 	AEMPTHY_THERSHOLD : almost empthy flag threshold
//
// Interface(Port - wire type)	:
// 	clk	: system clock
// 	rst_n	: active-low synchronous reset
// 	wr	: write request
// 	rd	: read request
// 	data_i	: input data
// 	data_o	: output data
// 	full_o	: FIFO full flag
// 	empty_o	: FIFO empty flag
// 	afull_o	: FIFO almost full flag
// 	aempty_o: FIFO almost empty flag
//
// Notes	:
// 	- Write operation ignored when FIFO is full
// 	- Read operation ignored when FIFO is empty
// 	- Simultaneous read/write allowed when FIFO not full/empty
//
//=========================================================================

module my_fifo #(
	//Parameters
	parameter	DATA_WIDTH 		= 32,
	parameter	FIFO_WIDTH		= 16,
	parameter	AFULL_THRESHOLD		= 13,
	parameter	AEMPTY_THRESHOLD	= 3

)
(	//Port
	input logic				clk,
	input logic				rst_n,
	input logic				wr,
	input logic				rd,
	input logic	[DATA_WIDTH-1:0]	data_i,
	output logic	[DATA_WIDTH-1:0]	data_o,
	output logic 				full_o,
	output logic 				empty_o,
	output logic 				afull_o,
	output logic 				aempty_o
);
	localparam FIFO_DEPTH	= $clog2(FIFO_WIDTH);		//FIFO_DEPTH = 4 for WIDTH 16
	
	//Internal regs & wires
	logic	[DATA_WIDTH-1:0]	mem[0:FIFO_WIDTH-1];	//FIFO circular buffer memory
	logic				full, empty;
	logic				full_n, empty_n;
	logic	[DATA_WIDTH-1:0]	data_r, data_r_n;	//data_r -> data_o
	logic	[FIFO_DEPTH:0]		r_ptr, w_ptr;		//read, write pointer with extra bit
	logic	[FIFO_DEPTH:0]		r_ptr_n, w_ptr_n;
	logic	[FIFO_DEPTH:0]		counter, counter_n;	//counter for threshold of afull & aempty	
	logic				wr_en, rd_en;

	assign wr_en	= wr & ~full;
	assign rd_en	= rd & ~empty;

	//Sequential logic
	always_ff @(posedge clk) begin
		if(!rst_n) begin
			for(int i = 0; i < FIFO_WIDTH; i=i+1) mem[i]	<= {(DATA_WIDTH){1'b0}};
			full 	<= 1'b0;
			empty	<= 1'b1;
			data_r	<= {(DATA_WIDTH){1'b0}};
			r_ptr	<= {(FIFO_DEPTH+1){1'b0}};		
			w_ptr	<= {(FIFO_DEPTH+1){1'b0}};
			counter	<= {(FIFO_DEPTH){1'b0}};		
		end else begin
			full	<= full_n;
			empty	<= empty_n;
			data_r	<= data_r_n;
			r_ptr	<= r_ptr_n;
			w_ptr	<= w_ptr_n;
			counter	<= counter_n;
			if(wr_en) mem[w_ptr[FIFO_DEPTH-1:0]] <= data_i;
		end
	end
	
	//Combinational logic
	always @(*) begin
		full_n		= full;
		empty_n		= empty;
		data_r_n	= data_r;
		r_ptr_n		= r_ptr;
		w_ptr_n		= w_ptr;
		counter_n	= counter;

		//Read operation
		if(rd_en) begin
			data_r_n	= mem[r_ptr[FIFO_DEPTH-1:0]]; //reads without extra bit
			r_ptr_n		= r_ptr + 1'b1;
			counter_n	= counter_n - 1'b1;
		end

		//Write operation
		if(wr_en) begin
			w_ptr_n		= w_ptr + 1'b1;
			counter_n	= counter_n + 1'b1;
		end

		//empty : pointers are same
		//full : pointers are same except extra bit
		empty_n		= (r_ptr_n == w_ptr_n);		      
		full_n		= ((r_ptr_n[FIFO_DEPTH] != w_ptr_n[FIFO_DEPTH])
				&&(r_ptr_n[FIFO_DEPTH-1:0] == w_ptr_n[FIFO_DEPTH-1:0]));
	end

	//Almost full, empty threshold, port assign
	assign afull_o		= (counter >= AFULL_THRESHOLD);
	assign aempty_o		= (counter <= AEMPTY_THRESHOLD);
	assign data_o		= data_r;
	assign full_o		= full;
	assign empty_o		= empty;
endmodule

fifo/RTL/TB/tb_fifo.sv
`timescale 1ns / 1ps

module tb_fifo();
    // parameters
    localparam DATA_WIDTH      = 32;
    localparam FIFO_WIDTH      = 16;
    localparam AFULL_THRESHOLD = 13;
    localparam AEMPTY_THRESHOLD= 3;

    // DUT signals
    reg                     clk;
    reg                     rst_n;
    reg                     wr;
    reg                     rd;
    reg  [DATA_WIDTH-1:0]   data_i;
    wire                    full_o;
    wire                    empty_o;
    wire                    afull_o;
    wire                    aempty_o;
    wire [DATA_WIDTH-1:0]   data_o;

    // DUT instance
    my_fifo #(
        .DATA_WIDTH(DATA_WIDTH),
        .FIFO_WIDTH(FIFO_WIDTH),
        .AFULL_THRESHOLD(AFULL_THRESHOLD),
        .AEMPTY_THRESHOLD(AEMPTY_THRESHOLD)
    ) dut (
        .clk       (clk),
        .rst_n     (rst_n),
        .wr        (wr),
        .rd        (rd),
        .data_i    (data_i),
        .full_o    (full_o),
        .empty_o   (empty_o),
        .afull_o   (afull_o),
        .aempty_o  (aempty_o),
        .data_o    (data_o)
    );

    initial begin
	    $dumpfile("wave.vcd");
	    $dumpvars(0, tb_fifo);
	end

    // clock gen
    initial clk = 0;
    always #5 clk = ~clk;  // 10ns period

    // tasks
    task automatic fifo_write(input [DATA_WIDTH-1:0] din);
    begin
        // wr를 한 클럭 동안 1로
        @(negedge clk);
        if (full_o) begin
            $display("[%0t] WARNING: write requested while FULL (ignored by DUT)", $time);
        end
        data_i = din;
        wr     = 1'b1;
        @(negedge clk);
        wr     = 1'b0;
    end
    endtask

    task automatic fifo_read(input [DATA_WIDTH-1:0] expected);
    begin
        @(negedge clk);
        if (empty_o) begin
            $display("[%0t] WARNING: read requested while EMPTY (ignored by DUT)", $time);
        end
        rd = 1'b1;
        @(posedge clk);  // 이 포지엣지에서 data_o가 업데이트됨
        #1; // 작은 delay 후 비교
        if (!empty_o) begin
            if (data_o !== expected) begin
                $display("[%0t] ERROR: read data mismatch. expected=0x%08h, got=0x%08h",
                         $time, expected, data_o);
                $stop;
            end else begin
                $display("[%0t] INFO: read OK. data=0x%08h", $time, data_o);
            end
        end
        @(negedge clk);
        rd = 1'b0;
    end
    endtask

    task automatic fifo_read_all;
    begin
        @(negedge clk);
        if (empty_o) begin
            $display("[%0t] WARNING: read requested while EMPTY (ignored by DUT)", $time);
        end
        rd = 1'b1;
        @(posedge clk);  // 이 포지엣지에서 data_o가 업데이트됨
        #1; // 작은 delay 후 비교
        if (!empty_o) begin
            $display("[%0t] INFO: read OK. data=0x%08h", $time, data_o);
        end
        @(negedge clk);
        rd = 1'b0;
    end
    endtask
    // main stimulus
    integer i;

    initial begin
        // init
        wr     = 0;
        rd     = 0;
        data_i = 0;

        // reset
        rst_n = 0;
        repeat (3) @(posedge clk);
        rst_n = 1;
        @(posedge clk);

        // -------------------------------
        // 1) Reset 상태 체크
        // -------------------------------
        $display("=== TEST 1: Reset state check ===");
        if (empty_o !== 1'b1 || full_o !== 1'b0) begin
            $display("[%0t] ERROR: Reset flags wrong. empty=%b full=%b", $time, empty_o, full_o);
            $stop;
        end
        if (aempty_o !== 1'b1 || afull_o !== 1'b0) begin
            $display("[%0t] ERROR: Reset almost flags wrong. aempty=%b afull=%b",
                     $time, aempty_o, afull_o);
            $stop;
        end

        // -------------------------------
        // 2) 단일 write/read
        // -------------------------------
        $display("=== TEST 2: Single write/read ===");
        fifo_write(32'hA5A5_0001);
        if (empty_o !== 1'b0) begin
            $display("[%0t] ERROR: After one write, empty should be 0", $time);
            $stop;
        end
        fifo_read(32'hA5A5_0001);
        if (empty_o !== 1'b1) begin
            $display("[%0t] ERROR: After read back, empty should be 1", $time);
            $stop;
        end

        // -------------------------------
        // 3) 가득 채워보기 (0~15)
        // -------------------------------
        $display("=== TEST 3: Fill FIFO ===");
        for (i = 0; i < FIFO_WIDTH; i = i+1) begin
            fifo_write(i);
            // afull_o 체크 (i+1이 AFULL_THRESHOLD 이상이면 HIGH 기대)
            if (i+1 >= AFULL_THRESHOLD && afull_o !== 1'b1) begin
                $display("[%0t] ERROR: afull_o should be 1 when count >= %0d (i=%0d)",
                         $time, AFULL_THRESHOLD, i);
                $stop;
            end
        end
        if (full_o !== 1'b1) begin
            $display("[%0t] ERROR: FIFO should be FULL after %0d writes", $time, FIFO_WIDTH);
            $stop;
        end
        if (empty_o !== 1'b0) begin
            $display("[%0t] ERROR: FIFO should not be EMPTY when full", $time);
            $stop;
        end

        // FULL 상태에서 write 시도
        $display("=== TEST 3-1: Write while FULL (should be ignored) ===");
        fifo_write(32'hDEAD_BEEF);  // w_en=0이라 무시되어야 함

        // -------------------------------
        // 4) 가득 찬 상태에서 모두 read
        // -------------------------------
        $display("=== TEST 4: Drain FIFO ===");
        for (i = 0; i < FIFO_WIDTH; i = i+1) begin
            fifo_read(i);  // 0~15 순서대로 나와야 함
            // aempty_o 체크: 남은 개수 <= threshold면 1
            if ((FIFO_WIDTH-1 - i) <= AEMPTY_THRESHOLD && aempty_o !== 1'b1) begin
                $display("[%0t] ERROR: aempty_o should be 1 when remaining <= %0d (after i=%0d)",
                         $time, AEMPTY_THRESHOLD, i);
                $stop;
            end
        end
        if (empty_o !== 1'b1 || full_o !== 1'b0) begin
            $display("[%0t] ERROR: After draining, empty should=1, full=0 (empty=%b full=%b)",
                     $time, empty_o, full_o);
            $stop;
        end

        // -------------------------------
        // 5) 중간 깊이에서 동시 read/write
        // -------------------------------
        $display("=== TEST 5: Simultaneous read/write (pipeline behavior) ===");
        // 8개 채우기 (100~107)
        for (i = 0; i < 8; i = i+1) begin
            fifo_write(32'h1000_0000 + i);
        end

        // 몇 사이클 동안 wr, rd 동시에 (200~203 쓰면서 100~103 읽힘 기대)
        for (i = 0; i < 4; i = i+1) begin
            @(negedge clk);
            // 동시 read/write
	    //display for each read, write pointer
	    $display("[%0t] INFO: read&write pointer : r_ptr=5'b%5b, w_ptr=5'b%5b", $time, dut.r_ptr, dut.w_ptr);
            wr     = 1'b1;
            rd     = 1'b1;
            data_i = 32'h2000_0000 + i;

            @(posedge clk);
            #1;
            // 이 시점의 data_o는 100~103 순서
            if (data_o !== (32'h1000_0000 + i)) begin
                $display("[%0t] ERROR: Simul R/W mismatch. expected=0x%08h, got=0x%08h",
                         $time, (32'h1000_0000 + i), data_o);
                $stop;
            end
            end
	for (i = 0; i < FIFO_WIDTH; i = i + 1) begin
		$display("[%0t] FIfo mem data (idx:%0d): 0x%08h",
                         $time, i, dut.mem[i]);
	end
	$finish;
            end
endmodule

fifo/SIM/wave.vcd
$date
	Wed Mar 18 18:19:24 2026
$end
$version
	Icarus Verilog
$end
$timescale
	1ps
$end
$scope module tb_fifo $end
$var wire 1 ! full_o $end
$var wire 1 " empty_o $end
$var wire 32 # data_o [31:0] $end
$var wire 1 $ afull_o $end
$var wire 1 % aempty_o $end
$var reg 1 & clk $end
$var reg 32 ' data_i [31:0] $end
$var reg 1 ( rd $end
$var reg 1 ) rst_n $end
$var reg 1 * wr $end
$var integer 32 + i [31:0] $end
$scope module dut $end
$var wire 1 & clk $end
$var wire 32 , data_i [31:0] $end
$var wire 32 - data_o [31:0] $end
$var wire 1 " empty_o $end
$var wire 1 ! full_o $end
$var wire 1 ( rd $end
$var wire 1 . rd_en $end
$var wire 1 ) rst_n $end
$var wire 1 * wr $end
$var wire 1 / wr_en $end
$var wire 1 $ afull_o $end
$var wire 1 % aempty_o $end
$var reg 5 0 counter [4:0] $end
$var reg 5 1 counter_n [4:0] $end
$var reg 32 2 data_r [31:0] $end
$var reg 32 3 data_r_n [31:0] $end
$var reg 1 4 empty $end
$var reg 1 5 empty_n $end
$var reg 1 6 full $end
$var reg 1 7 full_n $end
$var reg 5 8 r_ptr [4:0] $end
$var reg 5 9 r_ptr_n [4:0] $end
$var reg 5 : w_ptr [4:0] $end
$var reg 5 ; w_ptr_n [4:0] $end
$scope begin $ivl_for_loop0 $end
$var integer 32 < i [31:0] $end
$upscope $end
$upscope $end
$scope task apply_reset $end
$upscope $end
$scope task check_fifo_empty $end
$upscope $end
$scope task check_fifo_full $end
$upscope $end
$scope task check_reset_flags $end
$upscope $end
$scope task dump_mem $end
$upscope $end
$scope task fifo_read_no_check $end
$upscope $end
$scope task fifo_read_scoreboard $end
$upscope $end
$scope task fifo_simul_rw $end
$upscope $end
$scope task fifo_write $end
$upscope $end
$scope task init_signals $end
$upscope $end
$upscope $end
$enddefinitions $end
#0
$dumpvars
b0 <
bx ;
bx :
bx 9
bx 8
x7
x6
x5
x4
bx 3
bx 2
bx 1
bx 0
0/
0.
bx -
b0 ,
bx +
0*
0)
0(
b0 '
0&
x%
x$
bx #
x"
x!
$end
#5000
b0 1
b0 ;
b0 9
b0 3
15
07
0$
1%
b0 0
b0 :
b0 8
b0 #
b0 -
b0 2
1"
14
0!
06
b10000 <
1&
#10000
0&
#15000
b10000 <
1&
#20000
0&
#25000
b10000 <
1)
1&
#30000
0&
#35000
1&
#40000
05
b1 1
b1 ;
1/
1*
b10100101101001010000000000000001 '
b10100101101001010000000000000001 ,
0&
#45000
b10 1
b10 ;
b1 0
b1 :
0"
04
1&
#50000
b1 1
b1 ;
0/
b0 '
b0 ,
0*
0&
#55000
1&
#60000
15
b0 1
b1 9
b10100101101001010000000000000001 3
1.
1(
0&
#65000
0.
15
b0 1
b1 9
b10100101101001010000000000000001 3
b0 0
b1 8
b10100101101001010000000000000001 #
b10100101101001010000000000000001 -
b10100101101001010000000000000001 2
1"
14
1&
#70000
b0 +
0(
0&
#75000
1&
#80000
05
b1 1
b10 ;
1/
1*
0&
#85000
b10 1
b11 ;
b1 0
b10 :
0"
04
1&
#90000
b1 1
b10 ;
0/
b1 +
0*
0&
#95000
1&
#100000
b10 1
b11 ;
1/
1*
b1 '
b1 ,
0&
#105000
b11 1
b100 ;
b10 0
b11 :
1&
#110000
b10 1
b11 ;
0/
b10 +
b0 '
b0 ,
0*
0&
#115000
1&
#120000
b11 1
b100 ;
1/
1*
b10 '
b10 ,
0&
#125000
b100 1
b101 ;
b11 0
b100 :
1&
#130000
b11 1
b100 ;
0/
b11 +
b0 '
b0 ,
0*
0&
#135000
1&
#140000
b100 1
b101 ;
1/
1*
b11 '
b11 ,
0&
#145000
b101 1
b110 ;
0%
b100 0
b101 :
1&
#150000
b100 1
b101 ;
0/
b100 +
b0 '
b0 ,
0*
0&
#155000
1&
#160000
b101 1
b110 ;
1/
1*
b100 '
b100 ,
0&
#165000
b110 1
b111 ;
b101 0
b110 :
1&
#170000
b101 1
b110 ;
0/
b101 +
b0 '
b0 ,
0*
0&
#175000
1&
#180000
b110 1
b111 ;
1/
1*
b101 '
b101 ,
0&
#185000
b111 1
b1000 ;
b110 0
b111 :
1&
#190000
b110 1
b111 ;
0/
b110 +
b0 '
b0 ,
0*
0&
#195000
1&
#200000
b111 1
b1000 ;
1/
1*
b110 '
b110 ,
0&
#205000
b1000 1
b1001 ;
b111 0
b1000 :
1&
#210000
b111 1
b1000 ;
0/
b111 +
b0 '
b0 ,
0*
0&
#215000
1&
#220000
b1000 1
b1001 ;
1/
1*
b111 '
b111 ,
0&
#225000
b1001 1
b1010 ;
b1000 0
b1001 :
1&
#230000
b1000 1
b1001 ;
0/
b1000 +
b0 '
b0 ,
0*
0&
#235000
1&
#240000
b1001 1
b1010 ;
1/
1*
b1000 '
b1000 ,
0&
#245000
b1010 1
b1011 ;
b1001 0
b1010 :
1&
#250000
b1001 1
b1010 ;
0/
b1001 +
b0 '
b0 ,
0*
0&
#255000
1&
#260000
b1010 1
b1011 ;
1/
1*
b1001 '
b1001 ,
0&
#265000
b1011 1
b1100 ;
b1010 0
b1011 :
1&
#270000
b1010 1
b1011 ;
0/
b1010 +
b0 '
b0 ,
0*
0&
#275000
1&
#280000
b1011 1
b1100 ;
1/
1*
b1010 '
b1010 ,
0&
#285000
b1100 1
b1101 ;
b1011 0
b1100 :
1&
#290000
b1011 1
b1100 ;
0/
b1011 +
b0 '
b0 ,
0*
0&
#295000
1&
#300000
b1100 1
b1101 ;
1/
1*
b1011 '
b1011 ,
0&
#305000
b1101 1
b1110 ;
b1100 0
b1101 :
1&
#310000
b1100 1
b1101 ;
0/
b1100 +
b0 '
b0 ,
0*
0&
#315000
1&
#320000
b1101 1
b1110 ;
1/
1*
b1100 '
b1100 ,
0&
#325000
b1110 1
b1111 ;
1$
b1101 0
b1110 :
1&
#330000
b1101 1
b1110 ;
0/
b1101 +
b0 '
b0 ,
0*
0&
#335000
1&
#340000
b1110 1
b1111 ;
1/
1*
b1101 '
b1101 ,
0&
#345000
b1111 1
b10000 ;
b1110 0
b1111 :
1&
#350000
b1110 1
b1111 ;
0/
b1110 +
b0 '
b0 ,
0*
0&
#355000
1&
#360000
b1111 1
b10000 ;
1/
1*
b1110 '
b1110 ,
0&
#365000
17
b10000 1
b10001 ;
b1111 0
b10000 :
1&
#370000
b1111 1
b10000 ;
07
0/
b1111 +
b0 '
b0 ,
0*
0&
#375000
1&
#380000
17
b10000 1
b10001 ;
1/
1*
b1111 '
b1111 ,
0&
#385000
0/
17
b10000 1
b10001 ;
b10000 0
b10001 :
1!
16
1&
#390000
b10000 +
b0 '
b0 ,
0*
0&
#395000
1&
#400000
1*
b11011110101011011011111011101111 '
b11011110101011011011111011101111 ,
0&
#405000
1&
#410000
b0 +
b0 '
b0 ,
0*
0&
#415000
1&
#420000
07
b1111 1
b10 9
b0 3
1.
1(
0&
#425000
b1110 1
b11 9
b1 3
b1111 0
b10 8
b0 #
b0 -
b0 2
0!
06
1&
#430000
b1111 1
b10 9
b0 3
0.
b1 +
0(
0&
#435000
1&
#440000
b1110 1
b11 9
b1 3
1.
1(
0&
#445000
b1101 1
b100 9
b10 3
b1110 0
b11 8
b1 #
b1 -
b1 2
1&
#450000
b1110 1
b11 9
b1 3
0.
b10 +
0(
0&
#455000
1&
#460000
b1101 1
b100 9
b10 3
1.
1(
0&
#465000
b1100 1
b101 9
b11 3
b1101 0
b100 8
b10 #
b10 -
b10 2
1&
#470000
b1101 1
b100 9
b10 3
0.
b11 +
0(
0&
#475000
1&
#480000
b1100 1
b101 9
b11 3
1.
1(
0&
#485000
b1011 1
b110 9
b100 3
0$
b1100 0
b101 8
b11 #
b11 -
b11 2
1&
#490000
b1100 1
b101 9
b11 3
0.
b100 +
0(
0&
#495000
1&
#500000
b1011 1
b110 9
b100 3
1.
1(
0&
#505000
b1010 1
b111 9
b101 3
b1011 0
b110 8
b100 #
b100 -
b100 2
1&
#510000
b1011 1
b110 9
b100 3
0.
b101 +
0(
0&
#515000
1&
#520000
b1010 1
b111 9
b101 3
1.
1(
0&
#525000
b1001 1
b1000 9
b110 3
b1010 0
b111 8
b101 #
b101 -
b101 2
1&
#530000
b1010 1
b111 9
b101 3
0.
b110 +
0(
0&
#535000
1&
#540000
b1001 1
b1000 9
b110 3
1.
1(
0&
#545000
b1000 1
b1001 9
b111 3
b1001 0
b1000 8
b110 #
b110 -
b110 2
1&
#550000
b1001 1
b1000 9
b110 3
0.
b111 +
0(
0&
#555000
1&
#560000
b1000 1
b1001 9
b111 3
1.
1(
0&
#565000
b111 1
b1010 9
b1000 3
b1000 0
b1001 8
b111 #
b111 -
b111 2
1&
#570000
b1000 1
b1001 9
b111 3
0.
b1000 +
0(
0&
#575000
1&
#580000
b111 1
b1010 9
b1000 3
1.
1(
0&
#585000
b110 1
b1011 9
b1001 3
b111 0
b1010 8
b1000 #
b1000 -
b1000 2
1&
#590000
b111 1
b1010 9
b1000 3
0.
b1001 +
0(
0&
#595000
1&
#600000
b110 1
b1011 9
b1001 3
1.
1(
0&
#605000
b101 1
b1100 9
b1010 3
b110 0
b1011 8
b1001 #
b1001 -
b1001 2
1&
#610000
b110 1
b1011 9
b1001 3
0.
b1010 +
0(
0&
#615000
1&
#620000
b101 1
b1100 9
b1010 3
1.
1(
0&
#625000
b100 1
b1101 9
b1011 3
b101 0
b1100 8
b1010 #
b1010 -
b1010 2
1&
#630000
b101 1
b1100 9
b1010 3
0.
b1011 +
0(
0&
#635000
1&
#640000
b100 1
b1101 9
b1011 3
1.
1(
0&
#645000
b11 1
b1110 9
b1100 3
b100 0
b1101 8
b1011 #
b1011 -
b1011 2
1&
#650000
b100 1
b1101 9
b1011 3
0.
b1100 +
0(
0&
#655000
1&
#660000
b11 1
b1110 9
b1100 3
1.
1(
0&
#665000
b10 1
b1111 9
b1101 3
1%
b11 0
b1110 8
b1100 #
b1100 -
b1100 2
1&
#670000
b11 1
b1110 9
b1100 3
0.
b1101 +
0(
0&
#675000
1&
#680000
b10 1
b1111 9
b1101 3
1.
1(
0&
#685000
b1 1
b10000 9
b1110 3
b10 0
b1111 8
b1101 #
b1101 -
b1101 2
1&
#690000
b10 1
b1111 9
b1101 3
0.
b1110 +
0(
0&
#695000
1&
#700000
b1 1
b10000 9
b1110 3
1.
1(
0&
#705000
15
b0 1
b10001 9
b1111 3
b1 0
b10000 8
b1110 #
b1110 -
b1110 2
1&
#710000
b1 1
b10000 9
b1110 3
05
0.
b1111 +
0(
0&
#715000
1&
#720000
15
b0 1
b10001 9
b1111 3
1.
1(
0&
#725000
0.
15
b0 1
b10001 9
b1111 3
b0 0
b10001 8
b1111 #
b1111 -
b1111 2
1"
14
1&
#730000
b0 +
0(
0&
#735000
1&
#740000
05
b1 1
b10010 ;
1/
1*
b10000000000000000000000000000 '
b10000000000000000000000000000 ,
0&
#745000
b10 1
b10011 ;
b1 0
b10010 :
0"
04
1&
#750000
b1 1
b10010 ;
0/
b1 +
b0 '
b0 ,
0*
0&
#755000
1&
#760000
b10 1
b10011 ;
1/
1*
b10000000000000000000000000001 '
b10000000000000000000000000001 ,
0&
#765000
b11 1
b10100 ;
b10 0
b10011 :
1&
#770000
b10 1
b10011 ;
0/
b10 +
b0 '
b0 ,
0*
0&
#775000
1&
#780000
b11 1
b10100 ;
1/
1*
b10000000000000000000000000010 '
b10000000000000000000000000010 ,
0&
#785000
b100 1
b10101 ;
b11 0
b10100 :
1&
#790000
b11 1
b10100 ;
0/
b11 +
b0 '
b0 ,
0*
0&
#795000
1&
#800000
b100 1
b10101 ;
1/
1*
b10000000000000000000000000011 '
b10000000000000000000000000011 ,
0&
#805000
b101 1
b10110 ;
0%
b100 0
b10101 :
1&
#810000
b100 1
b10101 ;
0/
b100 +
b0 '
b0 ,
0*
0&
#815000
1&
#820000
b101 1
b10110 ;
1/
1*
b10000000000000000000000000100 '
b10000000000000000000000000100 ,
0&
#825000
b110 1
b10111 ;
b101 0
b10110 :
1&
#830000
b101 1
b10110 ;
0/
b101 +
b0 '
b0 ,
0*
0&
#835000
1&
#840000
b110 1
b10111 ;
1/
1*
b10000000000000000000000000101 '
b10000000000000000000000000101 ,
0&
#845000
b111 1
b11000 ;
b110 0
b10111 :
1&
#850000
b110 1
b10111 ;
0/
b110 +
b0 '
b0 ,
0*
0&
#855000
1&
#860000
b111 1
b11000 ;
1/
1*
b10000000000000000000000000110 '
b10000000000000000000000000110 ,
0&
#865000
b1000 1
b11001 ;
b111 0
b11000 :
1&
#870000
b111 1
b11000 ;
0/
b111 +
b0 '
b0 ,
0*
0&
#875000
1&
#880000
b1000 1
b11001 ;
1/
1*
b10000000000000000000000000111 '
b10000000000000000000000000111 ,
0&
#885000
b1001 1
b11010 ;
b1000 0
b11001 :
1&
#890000
b1000 1
b11001 ;
0/
b0 +
b0 '
b0 ,
0*
0&
#895000
1&
#900000
b11010 ;
b1000 1
b10010 9
b10000000000000000000000000000 3
1.
1/
1(
1*
b100000000000000000000000000000 '
b100000000000000000000000000000 ,
0&
#905000
b11011 ;
b1000 1
b10011 9
b10000000000000000000000000001 3
b11010 :
b10010 8
b10000000000000000000000000000 #
b10000000000000000000000000000 -
b10000000000000000000000000000 2
1&
#910000
b11010 ;
b10010 9
b10000000000000000000000000000 3
0.
0/
b1 +
b0 '
b0 ,
0(
0*
0&
#915000
1&
#920000
b11011 ;
b1000 1
b10011 9
b10000000000000000000000000001 3
1.
1/
1(
1*
b100000000000000000000000000001 '
b100000000000000000000000000001 ,
0&
#925000
b11100 ;
b1000 1
b10100 9
b10000000000000000000000000010 3
b11011 :
b10011 8
b10000000000000000000000000001 #
b10000000000000000000000000001 -
b10000000000000000000000000001 2
1&
#930000
b11011 ;
b10011 9
b10000000000000000000000000001 3
0.
0/
b10 +
b0 '
b0 ,
0(
0*
0&
#935000
1&
#940000
b11100 ;
b1000 1
b10100 9
b10000000000000000000000000010 3
1.
1/
1(
1*
b100000000000000000000000000010 '
b100000000000000000000000000010 ,
0&
#945000
b11101 ;
b1000 1
b10101 9
b10000000000000000000000000011 3
b11100 :
b10100 8
b10000000000000000000000000010 #
b10000000000000000000000000010 -
b10000000000000000000000000010 2
1&
#950000
b11100 ;
b10100 9
b10000000000000000000000000010 3
0.
0/
b11 +
b0 '
b0 ,
0(
0*
0&
#955000
1&
#960000
b11101 ;
b1000 1
b10101 9
b10000000000000000000000000011 3
1.
1/
1(
1*
b100000000000000000000000000011 '
b100000000000000000000000000011 ,
0&
#965000
b11110 ;
b1000 1
b10110 9
b10000000000000000000000000100 3
b11101 :
b10101 8
b10000000000000000000000000011 #
b10000000000000000000000000011 -
b10000000000000000000000000011 2
1&
#970000
b11101 ;
b10101 9
b10000000000000000000000000011 3
0.
0/
b100 +
b0 '
b0 ,
0(
0*
0&
#975000
1&
#980000
b111 1
b10110 9
b10000000000000000000000000100 3
1.
1(
0&
#985000
b110 1
b10111 9
b10000000000000000000000000101 3
b111 0
b10110 8
b10000000000000000000000000100 #
b10000000000000000000000000100 -
b10000000000000000000000000100 2
1&
#990000
b111 1
b10110 9
b10000000000000000000000000100 3
0.
0(
0&
#995000
1&
#1000000
b110 1
b10111 9
b10000000000000000000000000101 3
1.
1(
0&
#1005000
b101 1
b11000 9
b10000000000000000000000000110 3
b110 0
b10111 8
b10000000000000000000000000101 #
b10000000000000000000000000101 -
b10000000000000000000000000101 2
1&
#1010000
b110 1
b10111 9
b10000000000000000000000000101 3
0.
0(
0&
#1015000
1&
#1020000
b101 1
b11000 9
b10000000000000000000000000110 3
1.
1(
0&
#1025000
b100 1
b11001 9
b10000000000000000000000000111 3
b101 0
b11000 8
b10000000000000000000000000110 #
b10000000000000000000000000110 -
b10000000000000000000000000110 2
1&
#1030000
b101 1
b11000 9
b10000000000000000000000000110 3
0.
0(
0&
#1035000
1&
#1040000
b100 1
b11001 9
b10000000000000000000000000111 3
1.
1(
0&
#1045000
b11 1
b11010 9
b100000000000000000000000000000 3
b100 0
b11001 8
b10000000000000000000000000111 #
b10000000000000000000000000111 -
b10000000000000000000000000111 2
1&
#1050000
b100 1
b11001 9
b10000000000000000000000000111 3
0.
0(
0&
#1055000
1&
#1060000
b11 1
b11010 9
b100000000000000000000000000000 3
1.
1(
0&
#1065000
b10 1
b11011 9
b100000000000000000000000000001 3
1%
b11 0
b11010 8
b100000000000000000000000000000 #
b100000000000000000000000000000 -
b100000000000000000000000000000 2
1&
#1070000
b11 1
b11010 9
b100000000000000000000000000000 3
0.
0(
0&
#1075000
1&
#1080000
b10 1
b11011 9
b100000000000000000000000000001 3
1.
1(
0&
#1085000
b1 1
b11100 9
b100000000000000000000000000010 3
b10 0
b11011 8
b100000000000000000000000000001 #
b100000000000000000000000000001 -
b100000000000000000000000000001 2
1&
#1090000
b10 1
b11011 9
b100000000000000000000000000001 3
0.
0(
0&
#1095000
1&
#1100000
b1 1
b11100 9
b100000000000000000000000000010 3
1.
1(
0&
#1105000
15
b0 1
b11101 9
b100000000000000000000000000011 3
b1 0
b11100 8
b100000000000000000000000000010 #
b100000000000000000000000000010 -
b100000000000000000000000000010 2
1&
#1110000
b1 1
b11100 9
b100000000000000000000000000010 3
05
0.
0(
0&
#1115000
1&
#1120000
15
b0 1
b11101 9
b100000000000000000000000000011 3
1.
1(
0&
#1125000
0.
15
b0 1
b11101 9
b100000000000000000000000000011 3
b0 0
b11101 8
b100000000000000000000000000011 #
b100000000000000000000000000011 -
b100000000000000000000000000011 2
1"
14
1&
#1130000
0(
0&
