reg/RTL/reg.sv
// =======================================================================
// Module Name  : my_reg
// Author       : Kim Daeyeong
// Date         : 2026-03-18
//
// Description  :
//	Parameteriable N-bit register with enable signal and 
//	asynchronous actice-low reset
//
// Parameter	:
// 	N	: Data width of the register
//
// Ports	:
// 	clk	: Clock input
// 	rst_n	: Active-low reset
// 	en	: Load enable
// 	d	: N-bit input data to the register
// 	q	: N-bit output data from the register
//
// =======================================================================

module my_reg #(
	parameter	N = 1
)
(
	input logic		clk,
	input logic		rst_n,
	input logic		en,
	input logic	[N-1:0]	d,
	output logic	[N-1:0] q
);

always_ff @(posedge clk or negedge rst_n) begin
	if (!rst_n) q <= '0;
	else if (en) q <= d;
end

endmodule

reg/RTL/TB/tb_reg_golden_ref.sv
`timescale 1ns/1ps

module tb_my_reg;

    parameter int N = 8;

    logic clk;
    logic rst_n;
    logic en;
    logic [N-1:0] data_i;
    logic [N-1:0] data_o;

    // DUT
    my_reg #(
        .N(N)
    ) dut (
        .clk   (clk),
        .rst_n (rst_n),
        .en    (en),
        .d(data_i),
        .q(data_o)
    );
    
    initial begin
	   $dumpfile("wave.vcd");
	   $dumpvars(0, tb_my_reg);  
    end

    //------------------------------------------------------------
    // clock generation
    //------------------------------------------------------------
    initial clk = 0;
    always #5 clk = ~clk;

    //------------------------------------------------------------
    // golden reference model
    //------------------------------------------------------------
    logic [N-1:0] golden;

    always_ff @(posedge clk or negedge rst_n) begin
        if (!rst_n)
            golden <= '0;
        else if (en)
            golden <= data_i;
    end

    //------------------------------------------------------------
    // checker
    //------------------------------------------------------------
    always @(posedge clk) begin
        #1;
        if (data_o !== golden) begin
            $display("[%0t] ERROR: expected=%h got=%h",
                      $time, golden, data_o);
            $finish;
        end
    end

    //------------------------------------------------------------
    // stimulus
    //------------------------------------------------------------
    initial begin

        $display("===== TEST START =====");

        rst_n  = 0;
        en     = 0;
        data_i = 0;

        repeat(3) @(posedge clk);
        rst_n = 1;

        //--------------------------------------------------------
        // test enable load
        //--------------------------------------------------------
        repeat(5) begin
            @(posedge clk);
            en = 1;
            data_i = $urandom;
        end

        //--------------------------------------------------------
        // test hold behavior
        //--------------------------------------------------------
        @(posedge clk);
        en = 0;
        data_i = $urandom;

        repeat(3) @(posedge clk);

        //--------------------------------------------------------
        // random test
        //--------------------------------------------------------
        repeat(20) begin
            @(posedge clk);
            en = $urandom % 2;
            data_i = $urandom;
        end

        //--------------------------------------------------------
        // reset test
        //--------------------------------------------------------
        @(posedge clk);
        rst_n = 0;

        repeat(2) @(posedge clk);
        rst_n = 1;

        //--------------------------------------------------------
        // finish
        //--------------------------------------------------------
        repeat(5) @(posedge clk);

        $display("===== TEST PASS =====");
        $finish;

    end

endmodule

reg/SIM/wave.vcd
$date
	Wed Mar 18 19:40:27 2026
$end
$version
	Icarus Verilog
$end
$timescale
	1ps
$end
$scope module tb_my_reg $end
$var wire 8 ! data_o [7:0] $end
$var reg 1 " clk $end
$var reg 8 # data_i [7:0] $end
$var reg 1 $ en $end
$var reg 8 % golden [7:0] $end
$var reg 1 & rst_n $end
$scope module dut $end
$var wire 1 " clk $end
$var wire 8 ' d [7:0] $end
$var wire 1 $ en $end
$var wire 1 & rst_n $end
$var reg 8 ( q [7:0] $end
$upscope $end
$upscope $end
$enddefinitions $end
#0
$dumpvars
b0 (
b0 '
0&
b0 %
0$
b0 #
0"
b0 !
$end
#5000
1"
#10000
0"
#15000
1"
#20000
0"
#25000
1&
1"
#30000
0"
#35000
b100100 !
b100100 (
b100100 %
b100100 #
b100100 '
1$
1"
#40000
0"
#45000
b10000001 %
b10000001 !
b10000001 (
b10000001 #
b10000001 '
1"
#50000
0"
#55000
b1001 !
b1001 (
b1001 %
b1001 #
b1001 '
1"
#60000
0"
#65000
b1100011 %
b1100011 !
b1100011 (
b1100011 #
b1100011 '
1"
#70000
0"
#75000
b1101 !
b1101 (
b1101 %
b1101 #
b1101 '
1"
#80000
0"
#85000
b10001101 #
b10001101 '
0$
1"
#90000
0"
#95000
1"
#100000
0"
#105000
1"
#110000
0"
#115000
1"
#120000
0"
#125000
b10010 %
b10010 !
b10010 (
b10010 #
b10010 '
1$
1"
#130000
0"
#135000
b1101 !
b1101 (
b1101 %
b1101 #
b1101 '
1"
#140000
0"
#145000
b111101 #
b111101 '
0$
1"
#150000
0"
#155000
b10001100 !
b10001100 (
b10001100 %
b10001100 #
b10001100 '
1$
1"
#160000
0"
#165000
b11000110 %
b11000110 !
b11000110 (
b11000110 #
b11000110 '
1"
#170000
0"
#175000
b10101010 !
b10101010 (
b10101010 %
b10101010 #
b10101010 '
1"
#180000
0"
#185000
b1110111 %
b1110111 !
b1110111 (
b1110111 #
b1110111 '
1"
#190000
0"
#195000
b10001111 #
b10001111 '
0$
1"
#200000
0"
#205000
b11001110 #
b11001110 '
1"
#210000
0"
#215000
b11000101 #
b11000101 '
1"
#220000
0"
#225000
b10111101 #
b10111101 '
1"
#230000
0"
#235000
b1100101 !
b1100101 (
b1100101 %
b1100101 #
b1100101 '
1$
1"
#240000
0"
#245000
b1010 %
b1010 !
b1010 (
b1010 #
b1010 '
1"
#250000
0"
#255000
b100000 #
b100000 '
0$
1"
#260000
0"
#265000
b10011101 #
b10011101 '
1"
#270000
0"
#275000
b10011 #
b10011 '
1"
#280000
0"
#285000
b1010011 %
b1010011 !
b1010011 (
b1010011 #
b1010011 '
1$
1"
#290000
0"
#295000
b11010101 !
b11010101 (
b11010101 %
b11010101 #
b11010101 '
1"
#300000
0"
#305000
b10101110 #
b10101110 '
0$
1"
#310000
0"
#315000
b11001111 !
b11001111 (
b11001111 %
b11001111 #
b11001111 '
1$
1"
#320000
0"
#325000
b0 %
b0 !
b0 (
0&
1"
#330000
0"
#335000
1"
#340000
0"
#345000
b11001111 %
b11001111 !
b11001111 (
1&
1"
